{
  "name": "Public",
  "description": "Default role given to unauthenticated user.",
  "type": "public",
  "permissions": [
    {
      "action": "api::about-us.about-us.find"
    },
    {
      "action": "api::footer.footer.find"
    },
    {
      "action": "api::footer.footer.findOne"
    },
    {
      "action": "api::gallery.gallery.find"
    },
    {
      "action": "api::home-page.home-page.find"
    },
    {
      "action": "api::our-service.our-service.find"
    },
    {
      "action": "api::terms-and-condition.terms-and-condition.find"
    },
    {
      "action": "api::testimonial.testimonial.find"
    },
    {
      "action": "api::testimonial.testimonial.findOne"
    },
    {
      "action": "api::testimonials-page.testimonials-page.find"
    },
    {
      "action": "plugin::navigation.client.render"
    },
    {
      "action": "plugin::navigation.client.renderChild"
    },
    {
      "action": "plugin::users-permissions.auth.callback"
    },
    {
      "action": "plugin::users-permissions.auth.connect"
    },
    {
      "action": "plugin::users-permissions.auth.emailConfirmation"
    },
    {
      "action": "plugin::users-permissions.auth.forgotPassword"
    },
    {
      "action": "plugin::users-permissions.auth.register"
    },
    {
      "action": "plugin::users-permissions.auth.resetPassword"
    },
    {
      "action": "plugin::users-permissions.auth.sendEmailConfirmation"
    }
  ]
}